xlc_tools/__init__.py
xlc_tools/generate.py
xlc_tools-1.0.1.dist-info/METADATA
xlc_tools-1.0.1.dist-info/WHEEL
xlc_tools-1.0.1.dist-info/entry_points.txt
xlc_tools-1.0.1.dist-info/top_level.txt
xlc_tools-1.0.1.dist-info/zip-safe
xlc_tools-1.0.1.dist-info/RECORD
