Metadata-Version: 2.1
Name: xlc-tools
Version: 1.0.1
Summary: Internationalization(i18n) and Localization(l10n) of Multiple Languages
Home-page: https://github.com/bondbox/xlc/
Author: Mingzhe Zou
Author-email: zoumingzhe@outlook.com
License: GPLv2
Project-URL: Source Code, https://github.com/bondbox/xlc/
Project-URL: Bug Tracker, https://github.com/bondbox/xlc/issues
Project-URL: Documentation, https://github.com/bondbox/xlc/
Keywords: command-line,argparse,argcomplete
Platform: any
Classifier: Programming Language :: Python
Classifier: Programming Language :: Python :: 3
Requires-Python: >=3.8
Requires-Dist: xkits-command >=0.2
Requires-Dist: xlc >=1.0.1
